uwnet/__init__.py
uwnet/analysis/__init__.py
uwnet/analysis/sam_debug.py
uwnet/archive.py
uwnet/causal.py
uwnet/centderiv.py
uwnet/check_data.py
uwnet/columns.py
uwnet/constraints.py
uwnet/criticism/__init__.py
uwnet/criticism/evaluate.py
uwnet/criticism/imbalance.py
uwnet/data/blur.py
uwnet/data/preprocess.py
uwnet/data/reshape.py
uwnet/datasets.py
uwnet/debias.py
uwnet/estimators.py
uwnet/groupby.py
uwnet/jacobian.py
uwnet/logging.py
uwnet/loss.py
uwnet/metrics.py
uwnet/ml_models/__init__.py
uwnet/ml_models/nn/__init__.py
uwnet/ml_models/nn/datasets_handler.py
uwnet/ml_models/nn/sam_interface.py
uwnet/ml_models/nn/train.py
uwnet/ml_models/sklearn_generic/__init__.py
uwnet/ml_models/sklearn_generic/datasets_handler.py
uwnet/ml_models/sklearn_generic/sam_interface.py
uwnet/ml_models/sklearn_generic/train.py
uwnet/model.py
uwnet/modules.py
uwnet/ndimage_xarray.py
uwnet/normalization.py
uwnet/numpy_interface.py
uwnet/pre_post.py
uwnet/prepare_data.py
uwnet/sam_ngaqua.py
uwnet/samplers.py
uwnet/spectrum.py
uwnet/tensordict.py
uwnet/test_causal.py
uwnet/test_constraints.py
uwnet/test_datasets.py
uwnet/test_groupby.py
uwnet/test_integration.py
uwnet/test_jacobian.py
uwnet/test_loss.py
uwnet/test_model.py
uwnet/test_modules.py
uwnet/test_ndimage_xarray.py
uwnet/test_normalization.py
uwnet/test_tensordict.py
uwnet/test_timestepper.py
uwnet/test_train.py
uwnet/test_utils.py
uwnet/test_xarray_interface.py
uwnet/test_xcalc.py
uwnet/testing.py
uwnet/thermo.py
uwnet/timestepper.py
uwnet/training_plots.py
uwnet/utils.py
uwnet/wave/__init__.py
uwnet/wave/common.py
uwnet/wave/data.py
uwnet/wave/plots/__init__.py
uwnet/wave/plots/jacobian.py
uwnet/wave/serialize.py
uwnet/wave/spectra.py
uwnet/wave/tensordict.py
uwnet/wave/test_wave.py
uwnet/wave/utils.py
uwnet/wave/wave.py
uwnet/wave/xarray_interface.py
uwnet/xarray_interface.py
uwnet/xcalc.py
uwnet-0.9.2.dist-info/LICENSE
uwnet-0.9.2.dist-info/WHEEL
uwnet-0.9.2.dist-info/METADATA
uwnet-0.9.2.dist-info/RECORD
